flake8_unused_fixtures.py
flake8_unused_fixtures-0.3.3.dist-info/METADATA
flake8_unused_fixtures-0.3.3.dist-info/WHEEL
flake8_unused_fixtures-0.3.3.dist-info/entry_points.txt
flake8_unused_fixtures-0.3.3.dist-info/RECORD
