Metadata-Version: 2.3
Name: flake8_unused_fixtures
Version: 0.3.3
Summary: Warn about unnecessary fixtures in tests' definition.
License: BSD-3-Clause
Keywords: flake8,lint
Author: Marcin Binkowski
Author-email: binq661@gmail.com
Requires-Python: >=3.6,<4.0
Classifier: Environment :: Console
Classifier: Intended Audience :: Developers
Classifier: License :: OSI Approved :: BSD License
Classifier: Operating System :: OS Independent
Classifier: Programming Language :: Python
Classifier: Programming Language :: Python :: 3
Classifier: Programming Language :: Python :: 3.6
Classifier: Programming Language :: Python :: 3.7
Classifier: Programming Language :: Python :: 3.8
Classifier: Programming Language :: Python :: 3.9
Classifier: Programming Language :: Python :: 3.10
Classifier: Programming Language :: Python :: 3.11
Classifier: Programming Language :: Python :: 3.12
Classifier: Programming Language :: Python :: 3.13
Requires-Dist: astunparse
Requires-Dist: flake8
Requires-Dist: setuptools
Project-URL: Repository, https://github.com/MarcinBinkowski/flake8_unused_fixtures
